slack_approval/__init__.py
slack_approval/cli.py
slack_approval/slack_provision.py
slack_approval/slack_request.py
slack_approval/utils.py
slack_approval-0.1.7.1.dist-info/METADATA
slack_approval-0.1.7.1.dist-info/WHEEL
slack_approval-0.1.7.1.dist-info/entry_points.txt
slack_approval-0.1.7.1.dist-info/top_level.txt
slack_approval-0.1.7.1.dist-info/RECORD
