Metadata-Version: 2.1
Name: slack-approval
Version: 0.1.7.1
Summary: Library for managing and deploying a lightweight approval workflow based on Slack and GCP
Home-page: https://github.com/premisedata/slack-approval
Author: Austen
Author-email: austen.novis@gmail.com
License: MIT
Classifier: License :: OSI Approved :: MIT License
Classifier: Programming Language :: Python
Classifier: Programming Language :: Python :: 3
Classifier: Programming Language :: Python :: 3.7
Classifier: Programming Language :: Python :: 3.8
Classifier: Programming Language :: Python :: 3.9
Classifier: Programming Language :: Python :: 3.10
Classifier: Programming Language :: Python :: Implementation :: CPython
Classifier: Programming Language :: Python :: Implementation :: PyPy
Requires-Python: >=3.7.0
Requires-Dist: goblet-gcp >=0.9.2
Requires-Dist: slack-sdk ==3.18.1
